{
  "id": "367acb4f-4daa-5898-9771-81aae5ed2ef9",
  "category": "Healthcare",
  "thumbnailUrl": "assets/thumbnails/367acb4f-4daa-5898-9771-81aae5ed2ef9.png",
  "creator": {
    "name": "HeyForm",
    "avatarUrl": "assets/icons/heyform.png",
    "url": "https://heyform.net"
  },
  "name": "Patient Intake Form Template",
  "fields": [
    {
      "id": "EsCmSprAJzii",
      "title": "Full Name",
      "description": null,
      "kind": "full_name",
      "validations": {
        "required": true,
        "min": null,
        "max": null,
        "matchExpected": null
      },
      "properties": {
        "showButton": null,
        "buttonText": null,
        "hideMarks": null,
        "allowOther": null,
        "allowMultiple": null,
        "choices": null,
        "other": null,
        "shape": null,
        "total": null,
        "leftLabel": null,
        "centerLabel": null,
        "rightLabel": null,
        "start": null,
        "defaultCountryCode": null,
        "currency": null,
        "price": null,
        "format": null,
        "use12Hours": null,
        "score": null
      }
    },
    {
      "id": "Py9arrjfAl5J",
      "kind": "text"
    },
    {
      "id": "usdQtgM1mIUS",
      "title": "Date of Birth",
      "description": null,
      "kind": "date",
      "validations": {
        "required": true,
        "min": null,
        "max": null,
        "matchExpected": null
      },
      "properties": {
        "showButton": null,
        "buttonText": null,
        "hideMarks": null,
        "allowOther": null,
        "allowMultiple": null,
        "choices": null,
        "other": null,
        "shape": null,
        "total": null,
        "leftLabel": null,
        "centerLabel": null,
        "rightLabel": null,
        "start": null,
        "defaultCountryCode": null,
        "currency": null,
        "price": null,
        "format": "YYYY-MM-DD",
        "use12Hours": null,
        "score": null
      }
    },
    {
      "id": "vWhzrp8zy86a",
      "kind": "text"
    },
    {
      "id": "ABHkNCj8diOE",
      "title": "Age",
      "description": null,
      "kind": "number",
      "validations": {
        "required": true,
        "min": null,
        "max": null,
        "matchExpected": null
      },
      "properties": {
        "showButton": null,
        "buttonText": null,
        "hideMarks": null,
        "allowOther": null,
        "allowMultiple": null,
        "choices": null,
        "other": null,
        "shape": null,
        "total": null,
        "leftLabel": null,
        "centerLabel": null,
        "rightLabel": null,
        "start": null,
        "defaultCountryCode": null,
        "currency": null,
        "price": null,
        "format": null,
        "use12Hours": null,
        "score": null
      }
    },
    {
      "id": "JV3sEAWdYINo",
      "kind": "text"
    },
    {
      "id": "6b8QfRkbO64E",
      "title": "Contact Number",
      "description": null,
      "kind": "phone_number",
      "validations": {
        "required": true,
        "min": null,
        "max": null,
        "matchExpected": null
      },
      "properties": {
        "showButton": null,
        "buttonText": null,
        "hideMarks": null,
        "allowOther": null,
        "allowMultiple": null,
        "choices": null,
        "other": null,
        "shape": null,
        "total": null,
        "leftLabel": null,
        "centerLabel": null,
        "rightLabel": null,
        "start": null,
        "defaultCountryCode": "US",
        "currency": null,
        "price": null,
        "format": null,
        "use12Hours": null,
        "score": null
      }
    },
    {
      "id": "XvcZw2N1N4Xl",
      "kind": "text"
    },
    {
      "id": "XIW0pz76VsV5",
      "title": "Address",
      "description": null,
      "kind": "address",
      "validations": {
        "required": true,
        "min": null,
        "max": null,
        "matchExpected": null
      },
      "properties": {
        "showButton": null,
        "buttonText": null,
        "hideMarks": null,
        "allowOther": null,
        "allowMultiple": null,
        "choices": null,
        "other": null,
        "shape": null,
        "total": null,
        "leftLabel": null,
        "centerLabel": null,
        "rightLabel": null,
        "start": null,
        "defaultCountryCode": null,
        "currency": null,
        "price": null,
        "format": null,
        "use12Hours": null,
        "score": null
      }
    },
    {
      "id": "OKAAz9FBil8X",
      "kind": "text"
    },
    {
      "id": "JrLtRFEZ3yg9",
      "title": "MediCare / Insurance Number",
      "description": null,
      "kind": "short_text",
      "validations": {
        "required": true,
        "min": null,
        "max": null,
        "matchExpected": null
      },
      "properties": {
        "showButton": null,
        "buttonText": null,
        "hideMarks": null,
        "allowOther": null,
        "allowMultiple": null,
        "choices": null,
        "other": null,
        "shape": null,
        "total": null,
        "leftLabel": null,
        "centerLabel": null,
        "rightLabel": null,
        "start": null,
        "defaultCountryCode": null,
        "currency": null,
        "price": null,
        "format": null,
        "use12Hours": null,
        "score": null
      }
    },
    {
      "id": "2KfbdRHgcbUI",
      "kind": "text"
    },
    {
      "id": "t9EH8ATd9ONW",
      "title": "Any history of surgery or hospitalizations?",
      "description": null,
      "kind": "yes_no",
      "validations": {
        "required": true,
        "min": null,
        "max": null,
        "matchExpected": null
      },
      "properties": {
        "showButton": null,
        "buttonText": null,
        "hideMarks": null,
        "allowOther": null,
        "allowMultiple": null,
        "choices": [
          {
            "id": "ZYdL754wzySy",
            "label": "Yes",
            "image": null,
            "score": null,
            "isExpected": null
          },
          {
            "id": "PEIOQTVFb2d3",
            "label": "No",
            "image": null,
            "score": null,
            "isExpected": null
          }
        ],
        "other": null,
        "shape": null,
        "total": null,
        "leftLabel": null,
        "centerLabel": null,
        "rightLabel": null,
        "start": null,
        "defaultCountryCode": null,
        "currency": null,
        "price": null,
        "format": null,
        "use12Hours": null,
        "score": null
      }
    },
    {
      "id": "TM1AoFdFQIpR",
      "kind": "text"
    },
    {
      "id": "j9o4qMWxbbHm",
      "title": "Symptoms Diagnosed ",
      "description": null,
      "kind": "long_text",
      "validations": {
        "required": true,
        "min": null,
        "max": null,
        "matchExpected": null
      },
      "properties": {
        "showButton": null,
        "buttonText": null,
        "hideMarks": null,
        "allowOther": null,
        "allowMultiple": null,
        "choices": null,
        "other": null,
        "shape": null,
        "total": null,
        "leftLabel": null,
        "centerLabel": null,
        "rightLabel": null,
        "start": null,
        "defaultCountryCode": null,
        "currency": null,
        "price": null,
        "format": null,
        "use12Hours": null,
        "score": null
      }
    },
    {
      "id": "6zZT0QZGy0cs",
      "kind": "text"
    },
    {
      "id": "Jsgom4QiKOKh",
      "title": "Name of General Practitioner or Doctor",
      "description": null,
      "kind": "full_name",
      "validations": {
        "required": true,
        "min": null,
        "max": null,
        "matchExpected": null
      },
      "properties": {
        "showButton": null,
        "buttonText": null,
        "hideMarks": null,
        "allowOther": null,
        "allowMultiple": null,
        "choices": null,
        "other": null,
        "shape": null,
        "total": null,
        "leftLabel": null,
        "centerLabel": null,
        "rightLabel": null,
        "start": null,
        "defaultCountryCode": null,
        "currency": null,
        "price": null,
        "format": null,
        "use12Hours": null,
        "score": null
      }
    },
    {
      "id": "ueZl1Js7Pwx7",
      "kind": "text"
    }
  ],
  "hiddenFields": [],
  "translations": {},
  "logics": [],
  "variables": [],
  "themeSettings": {
    "theme": {
      "fontFamily": "Inter",
      "questionTextColor": "#3F3F46",
      "answerTextColor": "#3F3F46",
      "buttonBackground": "#3B82F6",
      "buttonTextColor": "#ffffff",
      "backgroundColor": "#fff",
      "backgroundImage": "https://forms.b-cdn.net/forms/Patient-Intake.jpeg",
      "backgroundBrightness": 79
    }
  }
}